statuscake/__init__.py
statuscake/api_client.py
statuscake/configuration.py
statuscake/exceptions.py
statuscake/model_utils.py
statuscake/rest.py
statuscake/api/__init__.py
statuscake/api/contact_groups_api.py
statuscake/api/locations_api.py
statuscake/api/maintenance_windows_api.py
statuscake/api/pagespeed_api.py
statuscake/api/ssl_api.py
statuscake/api/uptime_api.py
statuscake/apis/__init__.py
statuscake/model/__init__.py
statuscake/model/api_error.py
statuscake/model/api_response.py
statuscake/model/api_response_data.py
statuscake/model/contact_group.py
statuscake/model/contact_group_response.py
statuscake/model/contact_groups.py
statuscake/model/links.py
statuscake/model/maintenance_window.py
statuscake/model/maintenance_window_repeat_interval.py
statuscake/model/maintenance_window_response.py
statuscake/model/maintenance_window_state.py
statuscake/model/maintenance_windows.py
statuscake/model/metadata.py
statuscake/model/monitoring_location.py
statuscake/model/monitoring_location_status.py
statuscake/model/monitoring_locations.py
statuscake/model/pagespeed_test.py
statuscake/model/pagespeed_test_check_rate.py
statuscake/model/pagespeed_test_history.py
statuscake/model/pagespeed_test_history_result.py
statuscake/model/pagespeed_test_region.py
statuscake/model/pagespeed_test_response.py
statuscake/model/pagespeed_test_stats.py
statuscake/model/pagespeed_test_throttling.py
statuscake/model/pagespeed_tests.py
statuscake/model/pagination.py
statuscake/model/ssl_test.py
statuscake/model/ssl_test_check_rate.py
statuscake/model/ssl_test_flags.py
statuscake/model/ssl_test_mixed_content.py
statuscake/model/ssl_test_response.py
statuscake/model/ssl_tests.py
statuscake/model/uptime_test.py
statuscake/model/uptime_test_alert.py
statuscake/model/uptime_test_alerts.py
statuscake/model/uptime_test_check_rate.py
statuscake/model/uptime_test_history.py
statuscake/model/uptime_test_history_result.py
statuscake/model/uptime_test_overview.py
statuscake/model/uptime_test_period.py
statuscake_py-1.1.0b1.dist-info/LICENSE.txt
statuscake_py-1.1.0b1.dist-info/METADATA
statuscake_py-1.1.0b1.dist-info/WHEEL
statuscake_py-1.1.0b1.dist-info/top_level.txt
statuscake_py-1.1.0b1.dist-info/RECORD
