Metadata-Version: 2.1
Name: statuscake-py
Version: 1.1.0b1
Summary: StatusCake API
Home-page: https://github.com/StatusCakeDev/statuscake-py
Author: StatusCake
Author-email: support@statuscake.com
License: MIT
Keywords: python,sdk,statuscake
Requires-Python: >=3.6
License-File: LICENSE.txt
Requires-Dist: urllib3 (~=1.25.3)
Requires-Dist: python-dateutil (~=2.5.3)
